{
  "cli": {
    "version": ">= 18.0.0",
    "appVersionSource": "local"
  },
  "build": {
    "development": {
      "developmentClient": true,
      "distribution": "internal",
      "channel": "development",
      "env": {
        "EXPO_PUBLIC_SITE_URL": "https://staging.twobirdschurch.com"
      }
    },
    "preview": {
      "distribution": "internal",
      "channel": "preview",
      "env": {
        "EXPO_PUBLIC_SITE_URL": "https://community.twobirdschurch.com"
      }
    },
    "simulator": {
      "developmentClient": false,
      "channel": "simulator",
      "ios": {
        "simulator": true
      },
      "env": {
        "EXPO_PUBLIC_SITE_URL": "https://community.twobirdschurch.com"
      }
    },
    "production": {
      "autoIncrement": false,
      "channel": "production",
      "env": {
        "EXPO_PUBLIC_SITE_URL": "https://community.twobirdschurch.com"
      }
    }
  },
  "submit": {
    "production": {
      "ios": {
        "appleId": "jay@twobirdshealing.org",
        "ascAppId": "1563113528"
      }
    }
  }
}
